mutwo/common_generators/__init__.py
mutwo/common_generators/brown.py
mutwo/common_generators/brun.py
mutwo/common_generators/chomksy.py
mutwo/common_generators/constants.py
mutwo/common_generators/edwards.py
mutwo/common_generators/gray.py
mutwo/common_generators/koenig.py
mutwo/common_generators/lehmer.py
mutwo/common_generators/schillinger.py
mutwo/common_generators/toussaint.py
mutwo.ext_common_generators-0.8.1.dist-info/LICENSE
mutwo.ext_common_generators-0.8.1.dist-info/METADATA
mutwo.ext_common_generators-0.8.1.dist-info/WHEEL
mutwo.ext_common_generators-0.8.1.dist-info/top_level.txt
mutwo.ext_common_generators-0.8.1.dist-info/RECORD
