Metadata-Version: 2.1
Name: mutwo.ext-common-generators
Version: 0.8.1
Summary: Common generators extension for event based framework for generative art
Home-page: https://github.com/mutwo-org/mutwo.ext-common-generators
Author: Levin Eric Zimmermann
Author-email: levin.eric.zimmermann@posteo.eu
License: GPL
Project-URL: Documentation, https://mutwo.readthedocs.io/en/latest/
Platform: UNKNOWN
Requires-Python: >=3.9, <4
License-File: LICENSE
Requires-Dist: mutwo.ext-core (<1.00.0,>=0.54.0)
Requires-Dist: numpy (<2.00,>=1.18)
Requires-Dist: scipy (<2.0.0,>=1.4.1)
Requires-Dist: python-ranges (<1.0.0,>=0.2.0)
Requires-Dist: treelib (<2.0.0,>=1.6.1)
Provides-Extra: testing
Requires-Dist: nose ; extra == 'testing'
Requires-Dist: coveralls ; extra == 'testing'
